nyeok_dotenv/DirecoryChanger.py
nyeok_dotenv/EnvBase.py
nyeok_dotenv/__init__.py
nyeok_dotenv/py.typed
nyeok_dotenv-0.1.0.dist-info/METADATA
nyeok_dotenv-0.1.0.dist-info/WHEEL
nyeok_dotenv-0.1.0.dist-info/RECORD
