Metadata-Version: 2.1
Name: nyeok-dotenv
Version: 0.1.0
Summary: 
Author: kimkun07
Author-email: kimkun07@naver.com
Requires-Python: >=3.12,<4.0
Classifier: Programming Language :: Python :: 3
Classifier: Programming Language :: Python :: 3.12
Requires-Dist: python-dotenv (>=1.0.1,<2.0.0)
